<?xml version='1.0' encoding='UTF-8'?>
<object id="6inB9HZDFX8i" classes="section" acceptedChildren=":Proteus-any" acceptedParents=":Proteus-document section">
  <properties>
    <stringProperty name=":Proteus-name" category="general"><![CDATA[Requisitos generales del sistema]]></stringProperty>
    <markdownProperty name="comments" category="general"><![CDATA[]]></markdownProperty>
  </properties>
  <children>
    <child id="6usYBJp67ivh"/>
    <child id="7bsbackW6FMB"/>
    <child id="4GLxk6PdPGm9"/>
    <child id="3Cd3K38unypE"/>
    <child id="7rVyjVwa9eDc"/>
    <child id="6WUo7kABKn7h"/>
    <child id="7ovRAFdMLXsq"/>
  </children>
</object>
